gitingest/__init__.py
gitingest/__main__.py
gitingest/clone.py
gitingest/config.py
gitingest/entrypoint.py
gitingest/ingestion.py
gitingest/output_formatter.py
gitingest/query_parser.py
gitingest/schemas/__init__.py
gitingest/schemas/cloning.py
gitingest/schemas/filesystem.py
gitingest/schemas/ingestion.py
gitingest/utils/__init__.py
gitingest/utils/auth.py
gitingest/utils/compat_func.py
gitingest/utils/compat_typing.py
gitingest/utils/exceptions.py
gitingest/utils/file_utils.py
gitingest/utils/git_utils.py
gitingest/utils/ignore_patterns.py
gitingest/utils/ingestion_utils.py
gitingest/utils/logging_config.py
gitingest/utils/notebook.py
gitingest/utils/os_utils.py
gitingest/utils/pattern_utils.py
gitingest/utils/query_parser_utils.py
gitingest/utils/timeout_wrapper.py
gitingest-0.3.0.dist-info/licenses/LICENSE
server/__init__.py
server/__main__.py
server/form_types.py
server/main.py
server/metrics_server.py
server/models.py
server/query_processor.py
server/routers_utils.py
server/s3_utils.py
server/server_config.py
server/server_utils.py
server/routers/__init__.py
server/routers/dynamic.py
server/routers/index.py
server/routers/ingest.py
gitingest-0.3.0.dist-info/METADATA
gitingest-0.3.0.dist-info/WHEEL
gitingest-0.3.0.dist-info/entry_points.txt
gitingest-0.3.0.dist-info/top_level.txt
gitingest-0.3.0.dist-info/RECORD
