Metadata-Version: 2.4
Name: gitingest
Version: 0.3.0
Summary: CLI tool to analyze and create text dumps of codebases for LLMs
Author: Filip Christiansen
Author-email: Romain Courtois <romain@coderamp.io>
License: MIT License
Project-URL: homepage, https://gitingest.com
Project-URL: github, https://github.com/coderamp-labs/gitingest
Classifier: Development Status :: 3 - Alpha
Classifier: Intended Audience :: Developers
Classifier: License :: OSI Approved :: MIT License
Classifier: Programming Language :: Python :: 3.8
Classifier: Programming Language :: Python :: 3.9
Classifier: Programming Language :: Python :: 3.10
Classifier: Programming Language :: Python :: 3.11
Classifier: Programming Language :: Python :: 3.12
Classifier: Programming Language :: Python :: 3.13
Requires-Python: >=3.8
License-File: LICENSE
Requires-Dist: click>=8.0.0
Requires-Dist: httpx
Requires-Dist: loguru>=0.7.0
Requires-Dist: pathspec>=0.12.1
Requires-Dist: pydantic
Requires-Dist: python-dotenv
Requires-Dist: starlette>=0.40.0
Requires-Dist: strenum; python_version < "3.11"
Requires-Dist: tiktoken>=0.7.0
Requires-Dist: typing_extensions>=4.0.0; python_version < "3.10"
Provides-Extra: dev
Requires-Dist: eval-type-backport; extra == "dev"
Requires-Dist: pre-commit; extra == "dev"
Requires-Dist: pytest; extra == "dev"
Requires-Dist: pytest-asyncio; extra == "dev"
Requires-Dist: pytest-cov; extra == "dev"
Requires-Dist: pytest-mock; extra == "dev"
Provides-Extra: server
Requires-Dist: boto3>=1.28.0; extra == "server"
Requires-Dist: fastapi[standard]>=0.109.1; extra == "server"
Requires-Dist: prometheus-client; extra == "server"
Requires-Dist: sentry-sdk[fastapi]; extra == "server"
Requires-Dist: slowapi; extra == "server"
Requires-Dist: uvicorn>=0.11.7; extra == "server"
Dynamic: license-file
